{
    "yayinciisim": "Umut Can Arda",
    "token": "MTAwOTU5NDA5ODcwMjg4OTEwMA.GMhXI5.qcfwlUrtnvf3LJAfLe3JD8G5n-cZXy5GZqghgI",
    "prefix": "!",
    "botisim": "OtuzFps",
    "botlogo": "https://otuzfps.com/wp-content/uploads/2019/08/67411215_732785923841017_8014337660699017216_n.jpg",
    "yap覺mc覺isim": "Umut Can Arda",
    "yap覺mc覺logo": "https://otuzfps.com/wp-content/uploads/2019/08/67411215_732785923841017_8014337660699017216_n.jpg",
    "yeniuyekanaliid": "617479269345525966",
    "gidenuyekanaliid": "617479269345525966",
    "botchatid": "981970890298384444",
    "yeniuyerolid": "617479638012133439",
    "resimchatid": "617476341725659155"
    
}